{
  "alpine": {
    "description": "Alpine 3.20",
    "hide": false,
    "last_updated": "2024-07-04T08:37:55.000Z",
    "last_updated_url": "https://github.com/tainrs/base/actions/runs/9791149663",
    "latest": false,
    "tags": [
      "alpine",
      "alpine-3.2.0.0",
      "alpine-07e7771"
    ]
  },
  "jammy": {
    "description": "Ubuntu 22.04",
    "hide": false,
    "last_updated": "2024-07-04T08:39:31.000Z",
    "last_updated_url": "https://github.com/tainrs/base/actions/runs/9791165199",
    "latest": false,
    "tags": [
      "jammy",
      "jammy-3.2.0.0",
      "jammy-f224a02"
    ]
  },
  "noble": {
    "description": "Ubuntu 22.04",
    "hide": false,
    "last_updated": "2024-07-02T14:04:57.000Z",
    "last_updated_url": "https://github.com/tainrs/base/actions/runs/9762433891",
    "latest": false,
    "tags": [
      "noble",
      "noble-3.2.0.0",
      "noble-7038500"
    ]
  }
}
